Workbook

Sheet Dashboard
A2: Construction Finance Dashboard
A3: Prairie Field Services Ltd. | Results through 31-Aug-26 | CAD
A5: Selected case | B5: =Assumptions!B7 -> Base
A6: Revised cost budget | C6: Estimate at completion | E6: Cost variance | G6: Projected gross profit | I6: Gross margin | K6: Ending cash
A7: ='Financial Model'!D14 -> 7225000 | C7: ='Financial Model'!H14 -> 7390000 | E7: ='Financial Model'!I14 -> -165000 | G7: ='Financial Model'!K14 -> 2015000 | I7: ='Financial Model'!L14 -> 0.21424774 | K7: ='Cash Forecast'!O17 -> 105000
A9: Project | B9: Status | C9: Revised Budget | D9: EAC | E9: Cost Variance | F9: Contract Revenue | G9: Gross Profit | H9: Gross Margin | I9: Outstanding AR | J9: Management Attention
A10: ='Financial Model'!B9 -> Substation Equipment Replacement | B10: ='Financial Model'!S9 -> In Progress | C10: ='Financial Model'!D9 -> 1620000 | D10: ='Financial Model'!H9 -> 1675000 | E10: ='Financial Model'!I9 -> -55000 | F10: ='Financial Model'!J9 -> 2105000 | G10: ='Financial Model'!K9 -> 430000 | H10: ='Financial Model'!L9 -> 0.20427553 | I10: ='Financial Model'!O9 -> 250000 | J10: ='Financial Model'!T9 -> Cost overrun
A11: ='Financial Model'!B10 -> Natural Gas Pipeline Inspection | B11: ='Financial Model'!S10 -> In Progress | C11: ='Financial Model'!D10 -> 1180000 | D11: ='Financial Model'!H10 -> 1150000 | E11: ='Financial Model'!I10 -> 30000 | F11: ='Financial Model'!J10 -> 1545000 | G11: ='Financial Model'!K10 -> 395000 | H11: ='Financial Model'!L10 -> 0.25566343 | I11: ='Financial Model'!O10 -> 190000 | J11: ='Financial Model'!T10 -> On track
A12: ='Financial Model'!B11 -> Rural Power-Line Upgrade | B12: ='Financial Model'!S11 -> Delayed | C12: ='Financial Model'!D11 -> 2010000 | D12: ='Financial Model'!H11 -> 2130000 | E12: ='Financial Model'!I11 -> -120000 | F12: ='Financial Model'!J11 -> 2610000 | G12: ='Financial Model'!K11 -> 480000 | H12: ='Financial Model'!L11 -> 0.18390805 | I12: ='Financial Model'!O11 -> 220000 | J12: ='Financial Model'!T11 -> Cost overrun
A13: ='Financial Model'!B12 -> Compressor Station Maintenance | B13: ='Financial Model'!S12 -> In Progress | C13: ='Financial Model'!D12 -> 990000 | D13: ='Financial Model'!H12 -> 975000 | E13: ='Financial Model'!I12 -> 15000 | F13: ='Financial Model'!J12 -> 1275000 | G13: ='Financial Model'!K12 -> 300000 | H13: ='Financial Model'!L12 -> 0.23529412 | I13: ='Financial Model'!O12 -> 120000 | J13: ='Financial Model'!T12 -> On track
A14: ='Financial Model'!B13 -> Fleet Garage Construction | B14: ='Financial Model'!S13 -> Delayed | C14: ='Financial Model'!D13 -> 1425000 | D14: ='Financial Model'!H13 -> 1460000 | E14: ='Financial Model'!I13 -> -35000 | F14: ='Financial Model'!J13 -> 1870000 | G14: ='Financial Model'!K13 -> 410000 | H14: ='Financial Model'!L13 -> 0.21925134 | I14: ='Financial Model'!O13 -> 220000 | J14: ='Financial Model'!T13 -> Cost overrun
A15: Portfolio | C15: ='Financial Model'!D14 -> 7225000 | D15: ='Financial Model'!H14 -> 7390000 | E15: ='Financial Model'!I14 -> -165000 | F15: ='Financial Model'!J14 -> 9405000 | G15: ='Financial Model'!K14 -> 2015000 | H15: ='Financial Model'!L14 -> 0.21424774 | I15: ='Financial Model'!O14 -> 1000000
A18: Week | B18: Ending Cash | V18: Week | W18: Ending Cash
A19: ='Cash Forecast'!C8 -> 46272 | B19: ='Cash Forecast'!C17 -> 1140000 | V19: 7-Sep | W19: ='Cash Forecast'!C17 -> 1140000
A20: ='Cash Forecast'!D8 -> 46279 | B20: ='Cash Forecast'!D17 -> 1100000 | V20: 14-Sep | W20: ='Cash Forecast'!D17 -> 1100000
A21: ='Cash Forecast'!E8 -> 46286 | B21: ='Cash Forecast'!E17 -> 1025000 | V21: 21-Sep | W21: ='Cash Forecast'!E17 -> 1025000
A22: ='Cash Forecast'!F8 -> 46293 | B22: ='Cash Forecast'!F17 -> 920000 | V22: 28-Sep | W22: ='Cash Forecast'!F17 -> 920000
A23: ='Cash Forecast'!G8 -> 46300 | B23: ='Cash Forecast'!G17 -> 805000 | V23: 5-Oct | W23: ='Cash Forecast'!G17 -> 805000
A24: ='Cash Forecast'!H8 -> 46307 | B24: ='Cash Forecast'!H17 -> 745000 | V24: 12-Oct | W24: ='Cash Forecast'!H17 -> 745000
A25: ='Cash Forecast'!I8 -> 46314 | B25: ='Cash Forecast'!I17 -> 675000 | V25: 19-Oct | W25: ='Cash Forecast'!I17 -> 675000
A26: ='Cash Forecast'!J8 -> 46321 | B26: ='Cash Forecast'!J17 -> 580000 | V26: 26-Oct | W26: ='Cash Forecast'!J17 -> 580000
A27: ='Cash Forecast'!K8 -> 46328 | B27: ='Cash Forecast'!K17 -> 465000 | V27: 2-Nov | W27: ='Cash Forecast'!K17 -> 465000
A28: ='Cash Forecast'!L8 -> 46335 | B28: ='Cash Forecast'!L17 -> 375000 | V28: 9-Nov | W28: ='Cash Forecast'!L17 -> 375000
A29: ='Cash Forecast'!M8 -> 46342 | B29: ='Cash Forecast'!M17 -> 265000 | V29: 16-Nov | W29: ='Cash Forecast'!M17 -> 265000
A30: ='Cash Forecast'!N8 -> 46349 | B30: ='Cash Forecast'!N17 -> 180000 | V30: 23-Nov | W30: ='Cash Forecast'!N17 -> 180000
A31: ='Cash Forecast'!O8 -> 46356 | B31: ='Cash Forecast'!O17 -> 105000 | V31: 30-Nov | W31: ='Cash Forecast'!O17 -> 105000

Sheet Assumptions
A2: Assumptions
A3: Select one case. Yellow cells with blue text are editable.
A6: Case selector | B6: 2 | D6: Selector key
A7: Selected case | B7: =CHOOSE($B$6,"Best","Base","Worst") -> Base | D7: 1 | E7: Best
A8: Starting cash | B8: 1200000 | D8: 2 | E8: Base
D9: 3 | E9: Worst
A11: Remaining project cost adjustment | B11: Active selection | C11: =CHOOSE($B$6,C12,C13,C14) -> 0
B12: Best | C12: -0.05
B13: Base | C13: 0
B14: Worst | C14: 0.12
A16: Customer receipt factor | B16: Active selection | C16: =CHOOSE($B$6,C17,C18,C19) -> 1
B17: Best | C17: 1.05
B18: Base | C18: 1
B19: Worst | C19: 0.85
A21: Vendor payment factor | B21: Active selection | C21: =CHOOSE($B$6,C22,C23,C24) -> 1
B22: Best | C22: 0.97
B23: Base | C23: 1
B24: Worst | C24: 1.08
A26: Payroll and overhead factor | B26: Active selection | C26: =CHOOSE($B$6,C27,C28,C29) -> 1
B27: Best | C27: 0.98
B28: Base | C28: 1
B29: Worst | C29: 1.05
A31: Model note | B31: The active case changes project cost forecasts and the 13-week cash forecast.
A32: Reporting date | B32: 46265

Sheet Financial Model
A2: Project Financial Model
A3: Forecast at completion, profitability, billing and receivables by project
A5: Selected case | B5: =Assumptions!B7 -> Base
A6: Reporting date | B6: =Assumptions!B32 -> 46265
A8: Project ID | B8: Project Name | C8: Industry | D8: Revised Cost Budget | E8: Actual Cost to Date | F8: Open Commitments | G8: Estimate to Complete | H8: Estimate at Completion | I8: Cost Variance | J8: Revised Contract Revenue | K8: Projected Gross Profit | L8: Gross Margin | M8: Client Billings | N8: Cash Collected | O8: Outstanding Receivables | P8: Revenue Recognized | Q8: Unbilled Revenue | R8: Completion % | S8: Project Status | T8: Management Attention
A9: ='Project Master'!A6 -> P-101 | B9: ='Project Master'!B6 -> Substation Equipment Replacement | C9: ='Project Master'!C6 -> Utility | D9: ='Project Master'!H6+'Project Master'!I6 -> 1620000 | E9: =SUMIFS(Transactions!$H$6:$H$60,Transactions!$C$6:$C$60,$A9,Transactions!$D$6:$D$60,"Vendor Invoice")+SUMIFS(Transactions!$H$6:$H$60,Transactions!$C$6:$C$60,$A9,Transactions!$D$6:$D$60,"Accrual") -> 1025000 | F9: =SUMIFS(Transactions!$H$6:$H$60,Transactions!$C$6:$C$60,$A9,Transactions!$D$6:$D$60,"Commitment") -> 300000 | G9: =MAX(F9,'Project Master'!N6)*(1+Assumptions!$C$11) -> 650000 | H9: =E9+G9 -> 1675000 | I9: =D9-H9 -> -55000 | J9: ='Project Master'!J6+'Project Master'!K6 -> 2105000 | K9: =J9-H9 -> 430000 | L9: =IF(J9=0,"n.a.",K9/J9) -> 0.20427553 | M9: =SUMIFS(Transactions!$H$6:$H$60,Transactions!$C$6:$C$60,$A9,Transactions!$D$6:$D$60,"Client Billing") -> 1200000 | N9: =SUMIFS(Transactions!$H$6:$H$60,Transactions!$C$6:$C$60,$A9,Transactions!$D$6:$D$60,"Cash Receipt") -> 950000 | O9: =MAX(0,M9-N9) -> 250000 | P9: =J9*R9 -> 1368250 | Q9: =MAX(0,P9-M9) -> 168250 | R9: =_xlfn.XLOOKUP($A9,'Project Master'!$A$6:$A$10,'Project Master'!$L$6:$L$10,"Check project ID") -> 0.65 | S9: ='Project Master'!M6 -> In Progress | T9: =IF(I9<0,"Cost overrun",IF(O9>250000,"Collection follow-up",IF(S9="Delayed","Schedule review","On track"))) -> Cost overrun
A10: ='Project Master'!A7 -> P-102 | B10: ='Project Master'!B7 -> Natural Gas Pipeline Inspection | C10: ='Project Master'!C7 -> Oil & Gas | D10: ='Project Master'!H7+'Project Master'!I7 -> 1180000 | E10: =SUMIFS(Transactions!$H$6:$H$60,Transactions!$C$6:$C$60,$A10,Transactions!$D$6:$D$60,"Vendor Invoice")+SUMIFS(Transactions!$H$6:$H$60,Transactions!$C$6:$C$60,$A10,Transactions!$D$6:$D$60,"Accrual") -> 820000 | F10: =SUMIFS(Transactions!$H$6:$H$60,Transactions!$C$6:$C$60,$A10,Transactions!$D$6:$D$60,"Commitment") -> 230000 | G10: =MAX(F10,'Project Master'!N7)*(1+Assumptions!$C$11) -> 330000 | H10: =E10+G10 -> 1150000 | I10: =D10-H10 -> 30000 | J10: ='Project Master'!J7+'Project Master'!K7 -> 1545000 | K10: =J10-H10 -> 395000 | L10: =IF(J10=0,"n.a.",K10/J10) -> 0.25566343 | M10: =SUMIFS(Transactions!$H$6:$H$60,Transactions!$C$6:$C$60,$A10,Transactions!$D$6:$D$60,"Client Billing") -> 1050000 | N10: =SUMIFS(Transactions!$H$6:$H$60,Transactions!$C$6:$C$60,$A10,Transactions!$D$6:$D$60,"Cash Receipt") -> 860000 | O10: =MAX(0,M10-N10) -> 190000 | P10: =J10*R10 -> 1112400 | Q10: =MAX(0,P10-M10) -> 62400 | R10: =_xlfn.XLOOKUP($A10,'Project Master'!$A$6:$A$10,'Project Master'!$L$6:$L$10,"Check project ID") -> 0.72 | S10: ='Project Master'!M7 -> In Progress | T10: =IF(I10<0,"Cost overrun",IF(O10>250000,"Collection follow-up",IF(S10="Delayed","Schedule review","On track"))) -> On track
A11: ='Project Master'!A8 -> P-103 | B11: ='Project Master'!B8 -> Rural Power-Line Upgrade | C11: ='Project Master'!C8 -> Utility | D11: ='Project Master'!H8+'Project Master'!I8 -> 2010000 | E11: =SUMIFS(Transactions!$H$6:$H$60,Transactions!$C$6:$C$60,$A11,Transactions!$D$6:$D$60,"Vendor Invoice")+SUMIFS(Transactions!$H$6:$H$60,Transactions!$C$6:$C$60,$A11,Transactions!$D$6:$D$60,"Accrual") -> 1150000 | F11: =SUMIFS(Transactions!$H$6:$H$60,Transactions!$C$6:$C$60,$A11,Transactions!$D$6:$D$60,"Commitment") -> 510000 | G11: =MAX(F11,'Project Master'!N8)*(1+Assumptions!$C$11) -> 980000 | H11: =E11+G11 -> 2130000 | I11: =D11-H11 -> -120000 | J11: ='Project Master'!J8+'Project Master'!K8 -> 2610000 | K11: =J11-H11 -> 480000 | L11: =IF(J11=0,"n.a.",K11/J11) -> 0.18390805 | M11: =SUMIFS(Transactions!$H$6:$H$60,Transactions!$C$6:$C$60,$A11,Transactions!$D$6:$D$60,"Client Billing") -> 1350000 | N11: =SUMIFS(Transactions!$H$6:$H$60,Transactions!$C$6:$C$60,$A11,Transactions!$D$6:$D$60,"Cash Receipt") -> 1130000 | O11: =MAX(0,M11-N11) -> 220000 | P11: =J11*R11 -> 1513800 | Q11: =MAX(0,P11-M11) -> 163800 | R11: =_xlfn.XLOOKUP($A11,'Project Master'!$A$6:$A$10,'Project Master'!$L$6:$L$10,"Check project ID") -> 0.58 | S11: ='Project Master'!M8 -> Delayed | T11: =IF(I11<0,"Cost overrun",IF(O11>250000,"Collection follow-up",IF(S11="Delayed","Schedule review","On track"))) -> Cost overrun
A12: ='Project Master'!A9 -> P-104 | B12: ='Project Master'!B9 -> Compressor Station Maintenance | C12: ='Project Master'!C9 -> Oil & Gas | D12: ='Project Master'!H9+'Project Master'!I9 -> 990000 | E12: =SUMIFS(Transactions!$H$6:$H$60,Transactions!$C$6:$C$60,$A12,Transactions!$D$6:$D$60,"Vendor Invoice")+SUMIFS(Transactions!$H$6:$H$60,Transactions!$C$6:$C$60,$A12,Transactions!$D$6:$D$60,"Accrual") -> 800000 | F12: =SUMIFS(Transactions!$H$6:$H$60,Transactions!$C$6:$C$60,$A12,Transactions!$D$6:$D$60,"Commitment") -> 120000 | G12: =MAX(F12,'Project Master'!N9)*(1+Assumptions!$C$11) -> 175000 | H12: =E12+G12 -> 975000 | I12: =D12-H12 -> 15000 | J12: ='Project Master'!J9+'Project Master'!K9 -> 1275000 | K12: =J12-H12 -> 300000 | L12: =IF(J12=0,"n.a.",K12/J12) -> 0.23529412 | M12: =SUMIFS(Transactions!$H$6:$H$60,Transactions!$C$6:$C$60,$A12,Transactions!$D$6:$D$60,"Client Billing") -> 950000 | N12: =SUMIFS(Transactions!$H$6:$H$60,Transactions!$C$6:$C$60,$A12,Transactions!$D$6:$D$60,"Cash Receipt") -> 830000 | O12: =MAX(0,M12-N12) -> 120000 | P12: =J12*R12 -> 1058250 | Q12: =MAX(0,P12-M12) -> 108250 | R12: =_xlfn.XLOOKUP($A12,'Project Master'!$A$6:$A$10,'Project Master'!$L$6:$L$10,"Check project ID") -> 0.83 | S12: ='Project Master'!M9 -> In Progress | T12: =IF(I12<0,"Cost overrun",IF(O12>250000,"Collection follow-up",IF(S12="Delayed","Schedule review","On track"))) -> On track
A13: ='Project Master'!A10 -> P-105 | B13: ='Project Master'!B10 -> Fleet Garage Construction | C13: ='Project Master'!C10 -> Construction | D13: ='Project Master'!H10+'Project Master'!I10 -> 1425000 | E13: =SUMIFS(Transactions!$H$6:$H$60,Transactions!$C$6:$C$60,$A13,Transactions!$D$6:$D$60,"Vendor Invoice")+SUMIFS(Transactions!$H$6:$H$60,Transactions!$C$6:$C$60,$A13,Transactions!$D$6:$D$60,"Accrual") -> 700000 | F13: =SUMIFS(Transactions!$H$6:$H$60,Transactions!$C$6:$C$60,$A13,Transactions!$D$6:$D$60,"Commitment") -> 420000 | G13: =MAX(F13,'Project Master'!N10)*(1+Assumptions!$C$11) -> 760000 | H13: =E13+G13 -> 1460000 | I13: =D13-H13 -> -35000 | J13: ='Project Master'!J10+'Project Master'!K10 -> 1870000 | K13: =J13-H13 -> 410000 | L13: =IF(J13=0,"n.a.",K13/J13) -> 0.21925134 | M13: =SUMIFS(Transactions!$H$6:$H$60,Transactions!$C$6:$C$60,$A13,Transactions!$D$6:$D$60,"Client Billing") -> 860000 | N13: =SUMIFS(Transactions!$H$6:$H$60,Transactions!$C$6:$C$60,$A13,Transactions!$D$6:$D$60,"Cash Receipt") -> 640000 | O13: =MAX(0,M13-N13) -> 220000 | P13: =J13*R13 -> 916300 | Q13: =MAX(0,P13-M13) -> 56300 | R13: =_xlfn.XLOOKUP($A13,'Project Master'!$A$6:$A$10,'Project Master'!$L$6:$L$10,"Check project ID") -> 0.49 | S13: ='Project Master'!M10 -> Delayed | T13: =IF(I13<0,"Cost overrun",IF(O13>250000,"Collection follow-up",IF(S13="Delayed","Schedule review","On track"))) -> Cost overrun
A14: TOTAL | B14: Portfolio | D14: =SUM(D9:D13) -> 7225000 | E14: =SUM(E9:E13) -> 4495000 | F14: =SUM(F9:F13) -> 1580000 | G14: =SUM(G9:G13) -> 2895000 | H14: =SUM(H9:H13) -> 7390000 | I14: =SUM(I9:I13) -> -165000 | J14: =SUM(J9:J13) -> 9405000 | K14: =SUM(K9:K13) -> 2015000 | L14: =IF(J14=0,"n.a.",K14/J14) -> 0.21424774 | M14: =SUM(M9:M13) -> 5410000 | N14: =SUM(N9:N13) -> 4410000 | O14: =SUM(O9:O13) -> 1000000 | P14: =SUM(P9:P13) -> 5969000 | Q14: =SUM(Q9:Q13) -> 559000 | R14: =SUMPRODUCT(D9:D13,R9:R13)/SUM(D9:D13) -> 0.63506574

Sheet Cash Forecast
A2: 13-Week Cash Forecast
A3: Company-level cash forecast driven by the selected scenario
A5: Selected case | B5: =Assumptions!B7 -> Base
A6: Forecast start | B6: 46272
A8: Cash flow item | B8: Type | C8: 46272 | D8: 46279 | E8: 46286 | F8: 46293 | G8: 46300 | H8: 46307 | I8: 46314 | J8: 46321 | K8: 46328 | L8: 46335 | M8: 46342 | N8: 46349 | O8: 46356
A9: Beginning cash | B9: Calculated | C9: =Assumptions!$B$8 -> 1200000 | D9: =C17 -> 1140000 | E9: =D17 -> 1100000 | F9: =E17 -> 1025000 | G9: =F17 -> 920000 | H9: =G17 -> 805000 | I9: =H17 -> 745000 | J9: =I17 -> 675000 | K9: =J17 -> 580000 | ... O9: =N17 -> 180000
A10: Base customer receipts | B10: Input | C10: 420000 | D10: 310000 | E10: 510000 | F10: 275000 | G10: 460000 | H10: 350000 | I10: 540000 | J10: 295000 | K10: 480000 | L10: 330000 | M10: 525000 | N10: 360000 | O10: 600000
A11: Forecast customer receipts | B11: Calculated | C11: =C10*Assumptions!$C$16 -> 420000 | D11: =D10*Assumptions!$C$16 -> 310000 | E11: =E10*Assumptions!$C$16 -> 510000 | F11: =F10*Assumptions!$C$16 -> 275000 | G11: =G10*Assumptions!$C$16 -> 460000 | H11: =H10*Assumptions!$C$16 -> 350000 | I11: =I10*Assumptions!$C$16 -> 540000 | J11: =J10*Assumptions!$C$16 -> 295000 | ... O11: =O10*Assumptions!$C$16 -> 600000
A12: Base vendor payments | B12: Input | C12: 300000 | D12: 255000 | E12: 410000 | F12: 280000 | G12: 390000 | H12: 315000 | I12: 430000 | J12: 290000 | K12: 405000 | L12: 325000 | M12: 450000 | N12: 340000 | O12: 470000
A13: Forecast vendor payments | B13: Calculated | C13: =C12*Assumptions!$C$21 -> 300000 | D13: =D12*Assumptions!$C$21 -> 255000 | E13: =E12*Assumptions!$C$21 -> 410000 | F13: =F12*Assumptions!$C$21 -> 280000 | G13: =G12*Assumptions!$C$21 -> 390000 | H13: =H12*Assumptions!$C$21 -> 315000 | I13: =I12*Assumptions!$C$21 -> 430000 | J13: =J12*Assumptions!$C$21 -> 290000 | ... O13: =O12*Assumptions!$C$21 -> 470000
A14: Base payroll and overhead | B14: Input | C14: 180000 | D14: 95000 | E14: 175000 | F14: 100000 | G14: 185000 | H14: 95000 | I14: 180000 | J14: 100000 | K14: 190000 | L14: 95000 | M14: 185000 | N14: 105000 | O14: 205000
A15: Forecast payroll and overhead | B15: Calculated | C15: =C14*Assumptions!$C$26 -> 180000 | D15: =D14*Assumptions!$C$26 -> 95000 | E15: =E14*Assumptions!$C$26 -> 175000 | F15: =F14*Assumptions!$C$26 -> 100000 | G15: =G14*Assumptions!$C$26 -> 185000 | H15: =H14*Assumptions!$C$26 -> 95000 | I15: =I14*Assumptions!$C$26 -> 180000 | J15: =J14*Assumptions!$C$26 -> 100000 | ... O15: =O14*Assumptions!$C$26 -> 205000
A16: Net cash flow | B16: Calculated | C16: =C11-C13-C15 -> -60000 | D16: =D11-D13-D15 -> -40000 | E16: =E11-E13-E15 -> -75000 | F16: =F11-F13-F15 -> -105000 | G16: =G11-G13-G15 -> -115000 | H16: =H11-H13-H15 -> -60000 | I16: =I11-I13-I15 -> -70000 | J16: =J11-J13-J15 -> -95000 | ... O16: =O11-O13-O15 -> -75000
A17: Ending cash | B17: Calculated | C17: =C9+C16 -> 1140000 | D17: =D9+D16 -> 1100000 | E17: =E9+E16 -> 1025000 | F17: =F9+F16 -> 920000 | G17: =G9+G16 -> 805000 | H17: =H9+H16 -> 745000 | I17: =I9+I16 -> 675000 | J17: =J9+J16 -> 580000 | ... O17: =O9+O16 -> 105000

Sheet Project Master
A2: Project Master
A3: Fictional construction, utility and oil and gas projects
A5: Project ID | B5: Project Name | C5: Industry | D5: Project Manager | E5: Location | F5: Start Date | G5: Expected End Date | H5: Original Cost Budget | I5: Approved Cost Change Orders | J5: Original Contract Revenue | K5: Approved Revenue Change Orders | L5: Completion % | M5: Project Status | N5: Base Estimate to Complete
A6: P-101 | B6: Substation Equipment Replacement | C6: Utility | D6: Maya Chen | E6: Regina, SK | F6: 46037 | G6: 46371 | H6: 1500000 | I6: 120000 | J6: 1950000 | K6: 155000 | L6: 0.65 | M6: In Progress | N6: 650000
A7: P-102 | B7: Natural Gas Pipeline Inspection | C7: Oil & Gas | D7: Daniel Brooks | E7: Calgary, AB | F7: 46082 | G7: 46326 | H7: 1100000 | I7: 80000 | J7: 1450000 | K7: 95000 | L7: 0.72 | M7: In Progress | N7: 330000
A8: P-103 | B8: Rural Power-Line Upgrade | C8: Utility | D8: Priya Shah | E8: Moose Jaw, SK | F8: 46063 | G8: 46356 | H8: 1800000 | I8: 210000 | J8: 2350000 | K8: 260000 | L8: 0.58 | M8: Delayed | N8: 980000
A9: P-104 | B9: Compressor Station Maintenance | C9: Oil & Gas | D9: Ethan Cole | E9: Edmonton, AB | F9: 46113 | G9: 46295 | H9: 950000 | I9: 40000 | J9: 1220000 | K9: 55000 | L9: 0.83 | M9: In Progress | N9: 175000
A10: P-105 | B10: Fleet Garage Construction | C10: Construction | D10: Sophia Martin | E10: Regina, SK | F10: 46027 | G10: 46376 | H10: 1250000 | I10: 175000 | J10: 1650000 | K10: 220000 | L10: 0.49 | M10: Delayed | N10: 760000

Sheet Transactions
A2: Transactions
A3: Fictional invoice, accrual, commitment, billing and cash receipt records through 31-Aug-26
A5: Transaction ID | B5: Transaction Date | C5: Project ID | D5: Transaction Type | E5: Cost Category | F5: Counterparty | G5: Status | H5: Amount
A6: TX-0001 | B6: 46061 | C6: P-101 | D6: Vendor Invoice | E6: Materials | F6: Prairie Steel Ltd. | G6: Approved | H6: 210000
A7: TX-0002 | B7: 46089 | C7: P-101 | D7: Vendor Invoice | E7: Electrical | F7: Western Electrical Services | G7: Approved | H7: 185000
A8: TX-0003 | B8: 46120 | C8: P-101 | D8: Vendor Invoice | E8: Civil | F8: Northern Civil Works | G8: Approved | H8: 160000
A9: TX-0004 | B9: 46150 | C9: P-101 | D9: Vendor Invoice | E9: Equipment | F9: Summit Equipment Rentals | G9: Approved | H9: 235000
A10: TX-0005 | B10: 46181 | C10: P-101 | D10: Vendor Invoice | E10: Engineering | F10: Frontier Engineering Group | G10: Approved | H10: 150000
A11: TX-0006 | B11: 46262 | C11: P-101 | D11: Accrual | E11: Month-end Accrual | F11: Frontier Engineering Group | G11: Recorded | H11: 85000
A12: TX-0007 | B12: 46265 | C12: P-101 | D12: Commitment | E12: Open Purchase Order | F12: Northern Civil Works | G12: Open | H12: 300000
A13: TX-0008 | B13: 46157 | C13: P-101 | D13: Client Billing | E13: Progress Billing | F13: Prairie Energy Client | G13: Issued | H13: 650000
A14: TX-0009 | B14: 46218 | C14: P-101 | D14: Client Billing | E14: Progress Billing | F14: Prairie Energy Client | G14: Issued | H14: 550000
A15: TX-0010 | B15: 46193 | C15: P-101 | D15: Cash Receipt | E15: Customer Collection | F15: Prairie Energy Client | G15: Received | H15: 500000
A16: TX-0011 | B16: 46254 | C16: P-101 | D16: Cash Receipt | E16: Customer Collection | F16: Prairie Energy Client | G16: Received | H16: 450000
A17: TX-0012 | B17: 46062 | C17: P-102 | D17: Vendor Invoice | E17: Materials | F17: Prairie Steel Ltd. | G17: Approved | H17: 180000
... A60: TX-0055 | B60: 46258 | C60: P-105 | D60: Cash Receipt | E60: Customer Collection | F60: Prairie Energy Client | G60: Received | H60: 250000

Sheet Model Checks
A2: Model Checks
A3: Control totals and roll-forward checks. Differences should equal 0.00.
A6: Check | B6: Model Total | C6: Independent Total | D6: Difference | E6: Status
A7: Actual project costs | B7: ='Financial Model'!E14 -> 4495000 | C7: =SUMIFS(Transactions!$H$6:$H$60,Transactions!$D$6:$D$60,"Vendor Invoice")+SUMIFS(Transactions!$H$6:$H$60,Transactions!$D$6:$D$60,"Accrual") -> 4495000 | D7: =B7-C7 -> 0 | E7: =IF(ABS(D7)<0.01,"OK","Review") -> OK
A8: Client billings | B8: ='Financial Model'!M14 -> 5410000 | C8: =SUMIFS(Transactions!$H$6:$H$60,Transactions!$D$6:$D$60,"Client Billing") -> 5410000 | D8: =B8-C8 -> 0 | E8: =IF(ABS(D8)<0.01,"OK","Review") -> OK
A9: Cash collected | B9: ='Financial Model'!N14 -> 4410000 | C9: =SUMIFS(Transactions!$H$6:$H$60,Transactions!$D$6:$D$60,"Cash Receipt") -> 4410000 | D9: =B9-C9 -> 0 | E9: =IF(ABS(D9)<0.01,"OK","Review") -> OK
A10: Revised cost budget | B10: ='Financial Model'!D14 -> 7225000 | C10: =SUM('Project Master'!H6:H10)+SUM('Project Master'!I6:I10) -> 7225000 | D10: =B10-C10 -> 0 | E10: =IF(ABS(D10)<0.01,"OK","Review") -> OK
A11: Cash roll-forward | B11: =SUM('Cash Forecast'!C17:O17)-SUM('Cash Forecast'!C9:O9)-SUM('Cash Forecast'!C16:O16) -> 0 | C11: =0 -> 0 | D11: =B11-C11 -> 0 | E11: =IF(ABS(D11)<0.01,"OK","Review") -> OK

Sheet Guide
A2: Model Guide
A3: Portfolio workbook for construction, utility and energy finance roles
A6: Section | B6: Details
A7: Company | B7: Prairie Field Services Ltd. is a fictional contractor serving utility and energy clients.
A8: Purpose | B8: Demonstrate project accounting, financial modelling, cash forecasting, billing, receivables and management reporting.
A9: Data policy | B9: All names, transactions, amounts and assumptions are fictional. No current or former employer information is included.
A10: How to use | B10: Choose case 1, 2 or 3 on Assumptions. Update yellow cells with blue text. Review Dashboard, Financial Model and Cash Forecast.
A11: Best case | B11: Lower remaining project costs, stronger customer receipts and lower vendor and overhead payments.
A12: Base case | B12: Current estimate and payment assumptions.
A13: Worst case | B13: Higher remaining project costs, slower customer receipts and higher vendor and overhead payments.
A14: Key outputs | B14: Estimate at completion, cost variance, projected gross profit, gross margin, outstanding receivables and 13-week ending cash.
